threelog/__init__.py
threelog/logger_implementation.py
threelog/py.typed
threelog/three_logger.py
threelog/tracer_implementation.py
threelog/logger_implementations/console_logger.py
threelog/logger_implementations/null_logger.py
threelog/logger_implementations/python_logger.py
threelog/logger_implementations/uvicorn_logger.py
threelog-2.0.1.dist-info/licenses/LICENSE
threelog-2.0.1.dist-info/METADATA
threelog-2.0.1.dist-info/WHEEL
threelog-2.0.1.dist-info/top_level.txt
threelog-2.0.1.dist-info/RECORD
