Metadata-Version: 2.4
Name: ThreeLog
Version: 2.0.1
Summary: A flexible logging abstraction layer
License: MIT License
Project-URL: Homepage, https://github.com/thirdversion/threelog-py
Project-URL: Bug Tracker, https://github.com/thirdversion/threelog-py/issues
Requires-Python: >=3.10
License-File: LICENSE
Dynamic: license-file
